02_rtl/IP_LCD_timer_counter.sv
module IP_LCD_timer_counter #(
    parameter SIZE_DATA     = 8 ,
    parameter SIZE_FUNC     = 4 ,
    parameter FREQ          = 50_000_000
)(
    input logic         i_clk   ,
    input logic         i_rst_n ,
    input logic         i_en_lcd, 
    input logic         i_on_lcd,
    input logic         i_lcd_blon,
    input logic [SIZE_DATA-1:0] i_data,
    input logic [SIZE_FUNC-1:0] i_func,

    output logic [SIZE_DATA-1:0]    o_LCD_DATA  ,
    output logic                    o_LCD_E     ,
    output logic                    o_LCD_RW    ,
    output logic                    o_LCD_RS    ,
    output logic                    o_LCD_ON    ,
    output logic                    o_LCD_BLON  ,
    output logic                    o_done_lcd  
);

// Delay
parameter SIZE_DELAY = 32; 
logic [SIZE_DELAY-1:0] count, ncount;
assign ncount = count + 1'b1;
// localparam int  DELAY_15ms      = int'(0.015 * FREQ  + 0.5),
//                 DELAY_4_1_ms    = int'(0.0041 * FREQ + 0.5),
//                 DELAY_1_52ms    = int'(0.00152 * FREQ + 0.5),
//                 DELAY_100us     = int'(0.0001 * FREQ + 0.5),
//                 DELAY_37us      = int'(0.000037 * FREQ + 0.5),
//                 DELAY_230ns     = int'(0.00000023 * FREQ + 0.5);
localparam int  DELAY_15ms      = 50,
                DELAY_4_1_ms    = 30,
                DELAY_1_52ms    = 20,
                DELAY_100us     = 9,
                DELAY_37us      = 4,
                DELAY_230ns     = 2;
// localparam [SIZE_DELAY-1:0]  DELAY_15ms      = 32'd750000,
//                              DELAY_4_1_ms    = 32'd205000,
//                              DELAY_1_52ms    = 32'd76000,
//                              DELAY_100us     = 32'd5000,
//                              DELAY_37us      = 32'd1850,
//                              DELAY_230ns     = 32'd12;

// Func
logic [SIZE_FUNC-1:0] w_func_i, w_func_next;
localparam [SIZE_FUNC-1:0]  FUNC_INIT       = 0 ,
                            FUNC_SETCURSOR  = 1 ,
                            FUNC_CMD        = 2 ,
                            FUNC_DATA       = 3 ;
logic w_update_func;
assign w_update_func = (state == IDLE) ? 1'b1 : 1'b0;
assign w_func_i = w_update_func ? i_func : w_func_next;
always_ff @( posedge i_clk or negedge i_rst_n ) begin : save_i_func
    if(~i_rst_n) begin
        w_func_next <= '0;
    end else begin
        w_func_next <= w_func_i;
    end
end

// Data input
logic [SIZE_DATA-1:0] w_data_i, w_data_next;
logic w_update_data;
assign w_update_data = (state == IDLE) ? 1'b1 : 1'b0;
assign w_data_i = w_update_data ? i_data : w_data_next;
always_ff @( posedge i_clk or negedge i_rst_n ) begin : save_i_data
    if(~i_rst_n) begin
        w_data_next <= '0;
    end else begin
        w_data_next <= w_data_i;
    end
end

// CMD
localparam [SIZE_DATA-1:0] CMD_CLEAR_DISPLAY     = 8'h01, // Xóa màn hình
                           CMD_RETURN_HOME       = 8'h02, // Đưa con trỏ về đầu
                           CMD_ENTRY_INCREASE    = 8'h06, // Tăng địa chỉ, không dịch màn hình
                           CMD_DISPLAY_OFF       = 8'h08, // Tắt hiển thị
                           CMD_DISPLAY_ON        = 8'h0C, // Bật hiển thị, tắt con trỏ
                           CMD_INIT_LCD          = 8'h38, // Chế độ 8-bit, 2 dòng, font 5x8
                           CMD_LINE_1            = 8'h80,
                           CMD_LINE_2            = 8'hC0;

// The case of LCD
parameter SIZE_STATE = 32;
logic [SIZE_STATE-1:0] state, nstate;
localparam  [SIZE_STATE-1:0]    IDLE            = 0 ,
                                INIT_SETUP      = 1 ,
                                INIT_WAIT       = 2 ,
                                INIT_STEP       = 3 ,
                                SETCURSOR_SETUP = 4 ,
                                SETCURSOR_WAIT  = 5 ,
                                CMD_SETUP       = 7 ,
                                CMD_WAIT        = 8 ,
                                DATA_SETUP      = 9 ,
                                DATA_WAIT       = 10,
                                DONE            = 11,
                                DONE_WAIT       = 12,
                                INIT_DONE       = 13,
                                INIT_DONE_WAIT  = 14;

// State INIT
parameter SIZE_STEP = 9;
logic [SIZE_STEP-1:0] init_step, ninit_step;
assign ninit_step = init_step + 1;

always @(*) begin : proc_next_state
    case (state)
        IDLE: begin
            case (w_func_i)
                FUNC_INIT:
                    nstate = (i_en_lcd) ? INIT_SETUP : IDLE;
                FUNC_SETCURSOR:
                    nstate = (i_en_lcd) ? SETCURSOR_SETUP : IDLE;
                FUNC_CMD:
                    nstate = (i_en_lcd) ? CMD_SETUP : IDLE;
                FUNC_DATA:
                    nstate = (i_en_lcd) ? DATA_SETUP : IDLE;
                default:
                    nstate = IDLE;
            endcase
        end 
        INIT_SETUP: begin
            nstate = INIT_STEP;
        end
        INIT_STEP:
            nstate = (init_step > 8) ? IDLE : INIT_WAIT;
        INIT_WAIT: begin
            case (init_step)
                0       : nstate = (count == DELAY_15ms) ? INIT_STEP : INIT_WAIT;
                1       : nstate = (count == DELAY_4_1_ms) ? INIT_DONE : INIT_WAIT;
                2, 3    : nstate = (count == DELAY_100us) ? INIT_DONE : INIT_WAIT;
                4, 7, 8 : nstate = (count == DELAY_37us) ? INIT_DONE : INIT_WAIT;
                5, 6    : nstate = (count == DELAY_1_52ms) ? INIT_DONE : INIT_WAIT;
                default : nstate = INIT_DONE;
            endcase
        end
        INIT_DONE: 
            nstate = INIT_DONE_WAIT;
        INIT_DONE_WAIT:
            nstate = (count == DELAY_230ns) ? INIT_STEP : INIT_DONE_WAIT;
        SETCURSOR_SETUP:
            nstate = SETCURSOR_WAIT;
        SETCURSOR_WAIT:
            nstate = (count == DELAY_37us) ? DONE : SETCURSOR_WAIT;
        CMD_SETUP:
            nstate = CMD_WAIT;
        CMD_WAIT: begin
            case (w_data_i)
                CMD_CLEAR_DISPLAY, CMD_RETURN_HOME:
                    nstate = (count == DELAY_1_52ms) ? DONE : CMD_WAIT;
                default:
                    nstate = (count == DELAY_37us) ? DONE : CMD_WAIT;
            endcase
        end
        DATA_SETUP:
            nstate = DATA_WAIT;
        DATA_WAIT:
            nstate = (count == DELAY_37us) ? DONE : DATA_WAIT;
        DONE:
            nstate = DONE_WAIT;
        DONE_WAIT: 
            nstate = (count == DELAY_230ns) ? IDLE : DONE_WAIT;
        default:
            nstate = IDLE;
    endcase
end

always_ff @( posedge i_clk or negedge i_rst_n ) begin : proc_state_next_ff
    if(~i_rst_n) 
        state <= IDLE;
    else 
        state <= nstate;
end

always_ff @( posedge i_clk or negedge i_rst_n ) begin : proc_state_count
    if(~i_rst_n) begin
        count       <= '0;
    end else begin
        case (state)
            INIT_WAIT, INIT_DONE_WAIT, SETCURSOR_WAIT, CMD_WAIT, DATA_WAIT, DONE_WAIT: 
                count       <= ncount;
            default: 
                count       <= '0;
        endcase
    end
end
always_ff @( posedge i_clk or negedge i_rst_n ) begin : proc_state_init_step
    if(~i_rst_n) begin
        init_step   <= '0;
    end else begin
        case (state)
            IDLE, INIT_SETUP:
                init_step   <= '0;
            INIT_STEP: 
                init_step   <= ninit_step;
            default: 
                init_step   <= init_step;
        endcase
    end
end
always_ff @( posedge i_clk or negedge i_rst_n ) begin : proc_o_LCD_DATA
    if(~i_rst_n) begin
        o_LCD_DATA <= '0;
    end else begin
        case (state)
            IDLE:
                o_LCD_DATA <= '0;
            INIT_STEP: begin
                case (init_step)
                    1, 2, 3: begin
                        o_LCD_DATA <= CMD_INIT_LCD;
                    end
                    4: begin
                        o_LCD_DATA <= CMD_DISPLAY_OFF;
                    end
                    5: begin
                        o_LCD_DATA <= CMD_CLEAR_DISPLAY;
                    end
                    6: begin
                        o_LCD_DATA <= CMD_RETURN_HOME;
                    end
                    7: begin
                        o_LCD_DATA <= CMD_ENTRY_INCREASE;
                    end
                    8: begin
                        o_LCD_DATA <= CMD_DISPLAY_ON;
                    end
                    default: begin
                        o_LCD_DATA <= 8'h00;
                    end
                endcase
            end 
            SETCURSOR_SETUP: begin
                case (w_data_i[7:4])
                    4'h00: 
                        o_LCD_DATA <= CMD_LINE_1 + {4'h0, w_data_i[3:0]};
                    4'h01: 
                        o_LCD_DATA <= CMD_LINE_2 + {4'h0, w_data_i[3:0]};
                    default: 
                        o_LCD_DATA <= CMD_LINE_1;
                endcase
            end
            CMD_SETUP: 
                o_LCD_DATA <= w_data_i;
            DATA_SETUP: 
                o_LCD_DATA <= w_data_i;
            default: 
                o_LCD_DATA <= o_LCD_DATA;
        endcase
    end
end

always_ff @( posedge i_clk or negedge i_rst_n ) begin : proc_o_LCD_E
    if(~i_rst_n) begin
        o_LCD_E <= 1'b0;
    end else begin
        case (state)
            INIT_DONE       : o_LCD_E <= 1'b1;
            INIT_DONE_WAIT  : o_LCD_E <= 1'b1;
            DONE            : o_LCD_E <= 1'b1;
            DONE_WAIT       : o_LCD_E <= 1'b1;   
            default         : o_LCD_E <= 1'b0;
        endcase
    end
end

always_ff @( posedge i_clk or negedge i_rst_n ) begin : proc_o_LCD_RW
    if(~i_rst_n) begin
        o_LCD_RW <= 1'b0;
    end else begin
        o_LCD_RW <= 1'b0;
    end
end

always_ff @( posedge i_clk or negedge i_rst_n ) begin : proc_o_LCD_RS
    if(~i_rst_n) begin
        o_LCD_RS <= 1'b0;
    end else begin
        case (state)
            DATA_SETUP, DATA_WAIT: 
                o_LCD_RS <= 1'b1;
            INIT_DONE, INIT_DONE_WAIT, DONE, DONE_WAIT:
                o_LCD_RS <= o_LCD_RS;
            default: 
                o_LCD_RS <= 1'b0; 
        endcase
    end
end

assign o_LCD_ON = i_on_lcd;
assign o_LCD_BLON = i_lcd_blon;
always_ff @( posedge i_clk or negedge i_rst_n ) begin : proc_done_LCD
    if(~i_rst_n) begin
        o_done_lcd <= 1'b0;
    end else begin
        o_done_lcd <= ((state == DONE_WAIT && nstate == IDLE) || (init_step > 8)) ? 1'b1 : 1'b0;
    end
end

endmodule

03_test/Timer_counter/tb_IP_LCD_timer_counter.sv
// `timescale 1ps/1ps

// module tb_IP_LCD_timer_counter();

// parameter SIZE_DATA = 8;
// parameter SIZE_FUNC = 4;
// parameter CLK_PERIOD = 20;  // 50 MHz clock

// logic i_clk, i_rst_n, i_en_lcd, i_lcd_blon, o_LCD_ON, o_LCD_BLON;
// logic [SIZE_DATA-1:0] i_data, o_LCD_DATA;
// logic [SIZE_FUNC-1:0] i_func;
// logic o_LCD_E, o_LCD_RS, o_LCD_RW, o_done_lcd;

// // Instantiate the DUT
// IP_LCD_timer_counter #(
//     .SIZE_DATA      (SIZE_DATA),
//     .SIZE_FUNC      (SIZE_FUNC),
//     .FREQ           (50000)
// ) uut (
//     .i_clk          (i_clk      ),
//     .i_rst_n        (i_rst_n    ),
//     .i_en_lcd       (i_en_lcd   ),
//     .i_lcd_blon     (i_lcd_blon ),
//     .i_data         (i_data     ),
//     .i_func         (i_func     ),

//     .o_LCD_DATA     (o_LCD_DATA ),
//     .o_LCD_E        (o_LCD_E    ),
//     .o_LCD_RW       (o_LCD_RW   ),
//     .o_LCD_RS       (o_LCD_RS   ),
//     .o_LCD_ON       (o_LCD_ON   ),
//     .o_LCD_BLON     (o_LCD_BLON ),
//     .o_done_lcd     (o_done_lcd ) 
// );

// // Clock generator
// initial i_clk = 0;
// always #(CLK_PERIOD/2) i_clk = ~i_clk;

// // Dump file
// initial begin
//     $dumpfile("tb_IP_LCD_timer_counter.vcd");
//     $dumpvars(0, tb_IP_LCD_timer_counter);
// end

// // Display task
// task display_status;
//     input string test_name;
//     begin
//         $display("[%0t] TEST: %s", $time, test_name);
//         $display("  Inputs: func=%0d, data=%h, en_lcd=%b, blon=%b",
//                  i_func, i_data, i_en_lcd, i_lcd_blon);
//         $display("  Outputs: LCD_DATA=%h, E=%b, RW=%b, RS=%b, ON=%b, BLON=%b, done=%b",
//                  o_LCD_DATA, o_LCD_E, o_LCD_RW, o_LCD_RS, o_LCD_ON, o_LCD_BLON, o_done_lcd);
//     end
// endtask

// // Wait for operation completion
// task wait_for_done;
//     begin
//         @(posedge o_done_lcd);
//         #(CLK_PERIOD*2);
//     end
// endtask

// // Test initialization sequence
// task test_init;
//     begin
//         $display("\n\n=== TESTING INITIALIZATION SEQUENCE ===");
//         i_func = 0;  // FUNC_INIT
//         i_en_lcd = 1;
//         i_lcd_blon = 1;
//         @(negedge i_clk);
        
//         // Check each step of initialization
//         repeat(9) begin
//             wait_for_done();
//             display_status("Init Sequence Step");
//         end
        
//         // Verify LCD is enabled
//         if (o_LCD_ON !== 1'b1 || o_LCD_BLON !== 1'b1) begin
//             $display("ERROR: LCD not enabled after initialization");
//             $finish;
//         end
//     end
// endtask

// // Test cursor positioning
// task test_cursor;
//     input [7:0] position;
//     begin
//         $display("\n\n=== TESTING CURSOR POSITIONING: %h ===", position);
//         i_func = 1;  // FUNC_SETCURSOR
//         i_data = position;
//         @(negedge i_clk);
//         wait_for_done();
//         display_status("Set Cursor");
        
//         // Verify correct address was set
//         if (position[7:4] == 4'h0) begin
//             if (o_LCD_DATA !== (8'h80 | position[3:0])) begin
//                 $display("ERROR: Line 1 position mismatch. Expected: %h, Got: %h",
//                          8'h80 | position[3:0], o_LCD_DATA);
//                 $finish;
//             end
//         end
//         else if (position[7:4] == 4'h1) begin
//             if (o_LCD_DATA !== (8'hC0 | position[3:0])) begin
//                 $display("ERROR: Line 2 position mismatch. Expected: %h, Got: %h",
//                          8'hC0 | position[3:0], o_LCD_DATA);
//                 $finish;
//             end
//         end
//     end
// endtask

// // Test LCD commands
// task test_command;
//     input [7:0] cmd;
//     input string cmd_name;
//     begin
//         $display("\n\n=== TESTING COMMAND: %s (%h) ===", cmd_name, cmd);
//         i_func = 2;  // FUNC_CMD
//         i_data = cmd;
//         @(negedge i_clk);
//         wait_for_done();
//         display_status(cmd_name);
        
//         // Verify command was sent correctly
//         if (o_LCD_DATA !== cmd || o_LCD_RS !== 1'b0) begin
//             $display("ERROR: Command not sent correctly");
//             $finish;
//         end
//     end
// endtask

// // Test data writing
// task test_data;
//     input [7:0] data;
//     begin
//         $display("\n\n=== TESTING DATA WRITE: %h (%c) ===", data, data);
//         i_func = 3;  // FUNC_DATA
//         i_data = data;
//         @(negedge i_clk);
//         wait_for_done();
//         display_status("Write Data");
        
//         // Verify data was sent correctly
//         if (o_LCD_DATA !== data || o_LCD_RS !== 1'b1) begin
//             $display("ERROR: Data not sent correctly");
//             $finish;
//         end
//     end
// endtask

// // Test backlight and enable control
// task test_control_signals;
//     begin
//         $display("\n\n=== TESTING CONTROL SIGNALS ===");
        
//         // Disable LCD
//         i_en_lcd = 0;
//         i_lcd_blon = 0;
//         #100;
//         if (o_LCD_ON !== 1'b0 || o_LCD_BLON !== 1'b0) begin
//             $display("ERROR: LCD should be disabled");
//             $finish;
//         end
        
//         // Re-enable LCD
//         i_en_lcd = 1;
//         i_lcd_blon = 1;
//         #100;
//         if (o_LCD_ON !== 1'b1 || o_LCD_BLON !== 1'b1) begin
//             $display("ERROR: LCD should be enabled");
//             $finish;
//         end
//     end
// endtask

// // Main test sequence
// initial begin
//     // Initialize inputs
//     i_rst_n = 0;
//     i_en_lcd = 0;
//     i_lcd_blon = 0;
//     i_func = 0;
//     i_data = 0;
    
//     // Apply reset
//     #100;
//     i_rst_n = 1;
//     #100;
    
//     // Test 1: Initialization sequence
//     test_init();
    
//     // Test 2: Control signals
//     test_control_signals();
    
//     // Test 3: Cursor positioning
//     test_cursor(8'h00);  // Line 1, position 0
//     // test_cursor(8'h0F);  // Line 1, position 15
//     // test_cursor(8'h10);  // Line 2, position 0
//     // test_cursor(8'h1F);  // Line 2, position 15
    
//     // Test 4: LCD commands
//     test_command(8'h01, "Clear Display");
//     // test_command(8'h02, "Return Home");
//     // test_command(8'h06, "Entry Mode Set");
//     test_command(8'h08, "Display Off");
//     // test_command(8'h0C, "Display On");
//     // test_command(8'h38, "Function Set");
    
//     // Test 5: Data writing
//     test_data(8'h41);  // 'A'
//     // test_data(8'h42);  // 'B'
//     // test_data(8'h43);  // 'C'
//     // test_data(8'h31);  // '1'
//     // test_data(8'h32);  // '2'
//     // test_data(8'h33);  // '3'
    
//     // Test 6: Mixed sequence
//     $display("\n\n=== TESTING MIXED SEQUENCE ===");
//     test_command(8'h01, "Clear Display");
//     test_cursor(8'h00);   // Line 1, position 0
//     test_data("H");
//     // test_data("e");
//     // test_data("l");
//     // test_data("l");
//     // test_data("o");
//     // test_cursor(8'h40);   // Line 2, position 0 (8'h40 = 8'hC0?)
//     // test_data("W");
//     // test_data("o");
//     // test_data("r");
//     // test_data("l");
//     // test_data("d");
//     // test_data("!");
    
//     // Test 7: Invalid function code
//     $display("\n\n=== TESTING INVALID FUNCTION ===");
//     i_func = 4;  // Invalid function code
//     @(negedge i_clk);
//     #100;
//     if (o_done_lcd !== 1'b0) begin
//         $display("ERROR: Should not complete for invalid function");
//         $finish;
//     end
    
//     // All tests passed
//     $display("\n\n====================================");
//     $display("ALL TESTS PASSED SUCCESSFULLY!");
//     $display("====================================");
//     $finish;
// end

// endmodule

`timescale 1ps/1ps
module tb_IP_LCD_timer_counter();

parameter SIZE_DATA = 8;
parameter SIZE_FUNC = 4;
parameter CLK_PERIOD = 20;  // 50 MHz clock

logic i_clk, i_rst_n, i_en_lcd, i_on_lcd, i_lcd_blon;
logic o_LCD_E, o_LCD_RW, o_LCD_RS, o_LCD_ON, o_LCD_BLON, o_done_lcd;
logic [SIZE_DATA-1:0] i_data, o_LCD_DATA;
logic [SIZE_FUNC-1:0] i_func;
IP_LCD_timer_counter #(
    .SIZE_DATA      (8) ,
    .SIZE_FUNC      (4) ,
    .FREQ           (50_000_000)
) uut (
    .i_clk          (i_clk),
    .i_rst_n        (i_rst_n),
    .i_en_lcd       (i_en_lcd), 
    .i_on_lcd       (i_on_lcd),
    .i_lcd_blon     (i_lcd_blon),
    .i_data         (i_data),
    .i_func         (i_func),

    .o_LCD_DATA     (o_LCD_DATA),
    .o_LCD_E        (o_LCD_E),
    .o_LCD_RW       (o_LCD_RW),
    .o_LCD_RS       (o_LCD_RS),
    .o_LCD_ON       (o_LCD_ON),
    .o_LCD_BLON     (o_LCD_BLON),
    .o_done_lcd     (o_done_lcd)
);

initial i_clk = 0;
always #(CLK_PERIOD/2) i_clk = ~i_clk;

initial begin
    $dumpfile("tb_IP_LCD_timer_counter.vcd");
    $dumpvars(0, tb_IP_LCD_timer_counter);
end

task display_testcase;
    input string testcase;
    begin
        $display("=========== Testcase: %s ===========", testcase);
    end
endtask 
task display_input;
    begin
        $display("| Time = %t \t| i_rst_n = %b \t| i_on_lcd = %b \t| i_lcd_blon = %b \t|", 
                    $time, i_rst_n, i_on_lcd, i_lcd_blon);
        $display("| Time = %t \t| i_en_lcd = %b \t| i_fun = %h \t| i_data = %h \t|", 
                    $time, i_en_lcd, i_func, i_data);
    end
endtask
task display_output;
    begin
        $display("| Time = %t \t| o_LCD_RW = %b \t| o_LCD_RS = %b \t| o_LCD_E = %b \t|", 
                    $time, o_LCD_RW, o_LCD_RS, o_LCD_E);
        $display("| Time = %t \t| o_LCD_DATA = %h \t| o_done_lcd = %b \t|", 
                    $time, o_LCD_DATA, o_done_lcd);
    end
endtask 
task wait_for_done;
    begin
        @(posedge o_done_lcd);
        #1;
    end
endtask
task wait_for_end;
    begin
        // @(negedge o_done_lcd);
        #20;
    end
endtask
task check_init;
    begin
        display_testcase("Init");
        @(posedge i_clk);
        i_func = 0;
        i_en_lcd = 1;
        i_data = 0;
        display_input();
        wait_for_done();
        display_output();
        wait_for_end();
        i_en_lcd = 0;
        if (o_LCD_ON !== 1'b1 || o_LCD_BLON !== 1'b1) begin
            $display("ERROR: LCD not enabled after initialization");
        end
        
    end
endtask
task check_cursor;
    input [7:0] cursor_data;
    begin
        display_testcase("Setcursor");
        @(posedge i_clk);
        i_func = 1;
        i_en_lcd = 1;
        i_data = cursor_data;
        display_input();
        wait_for_done();
        display_output();
        wait_for_end();
        i_en_lcd = 0;
        if (o_LCD_ON !== 1'b1 || o_LCD_BLON !== 1'b1) begin
            $display("ERROR: LCD not enabled after initialization");
        end
    end
endtask
task check_cmd;
    input [7:0] cmd_data;
    begin
        display_testcase("Command");
        @(posedge i_clk);
        i_func = 2;
        i_en_lcd = 1;
        i_data = cmd_data;
        display_input();
        wait_for_done();
        display_output();
        wait_for_end();
        i_en_lcd = 0;
        if (o_LCD_ON !== 1'b1 || o_LCD_BLON !== 1'b1) begin
            $display("ERROR: LCD not enabled after initialization");
        end
    end
endtask
task check_date;
    input [7:0] data_data;
    begin
        display_testcase("Command");
        @(posedge i_clk);
        i_func = 3;
        i_en_lcd = 1;
        i_data = data_data;
        display_input();
        wait_for_done();
        display_output();
        wait_for_end();
        i_en_lcd = 0;
        if (o_LCD_ON !== 1'b1 || o_LCD_BLON !== 1'b1) begin
            $display("ERROR: LCD not enabled after initialization");
        end
    end
endtask
task check_control_signal;
    begin
        display_testcase("Control Signal");
        i_on_lcd = 0;
        i_lcd_blon = 0;
        #(CLK_PERIOD*10);
        if (o_LCD_ON !== 1'b0 || o_LCD_BLON !== 1'b0) begin
            $display("ERROR: LCD should be disabled");
        end
        display_output();
        #(CLK_PERIOD*10);
        i_on_lcd = 1;
        i_lcd_blon = 1;
        #(CLK_PERIOD*10);
        if (o_LCD_ON !== 1'b0 || o_LCD_BLON !== 1'b0) begin
            $display("ERROR: LCD should be disabled");
        end
        display_output();
    end
endtask

initial begin
    i_rst_n = 0;
    i_en_lcd = 0;
    i_on_lcd = 0;
    i_lcd_blon = 0;
    i_func = 0;
    i_data = 0;
    #100;
    i_rst_n = 1;
    check_control_signal();

    #100;
    check_init();

    #100;
    check_cursor(8'h00);
    #20;
    check_cursor(8'h05);
    #20;
    check_cursor(8'h10);
    #20;
    check_cursor(8'h15);

    #100;
    check_cmd(8'h01);
    #20;
    check_cmd(8'h02);
    #20;
    check_cmd(8'h06);

    #100;
    check_date(8'h29);
    #20;
    check_date(8'h30);

    #1000;
    $display("Finish test");
    $finish;
end

endmodule

03_test/Timer_counter/tb_IP_LCD_timer_counter.vcd
$version Generated by VerilatedVcd $end
$timescale 1ps $end
 $scope module TOP $end
  $scope module tb_IP_LCD_timer_counter $end
   $var wire 32 : SIZE_DATA [31:0] $end
   $var wire 32 ; SIZE_FUNC [31:0] $end
   $var wire 32 < CLK_PERIOD [31:0] $end
   $var wire 1 6 i_clk $end
   $var wire 1 # i_rst_n $end
   $var wire 1 $ i_en_lcd $end
   $var wire 1 % i_on_lcd $end
   $var wire 1 & i_lcd_blon $end
   $var wire 1 ) o_LCD_E $end
   $var wire 1 * o_LCD_RW $end
   $var wire 1 + o_LCD_RS $end
   $var wire 1 % o_LCD_ON $end
   $var wire 1 & o_LCD_BLON $end
   $var wire 1 , o_done_lcd $end
   $var wire 8 ' i_data [7:0] $end
   $var wire 8 - o_LCD_DATA [7:0] $end
   $var wire 4 ( i_func [3:0] $end
   $scope module uut $end
    $var wire 32 : SIZE_DATA [31:0] $end
    $var wire 32 ; SIZE_FUNC [31:0] $end
    $var wire 32 = FREQ [31:0] $end
    $var wire 1 6 i_clk $end
    $var wire 1 # i_rst_n $end
    $var wire 1 $ i_en_lcd $end
    $var wire 1 % i_on_lcd $end
    $var wire 1 & i_lcd_blon $end
    $var wire 8 ' i_data [7:0] $end
    $var wire 4 ( i_func [3:0] $end
    $var wire 8 - o_LCD_DATA [7:0] $end
    $var wire 1 ) o_LCD_E $end
    $var wire 1 * o_LCD_RW $end
    $var wire 1 + o_LCD_RS $end
    $var wire 1 % o_LCD_ON $end
    $var wire 1 & o_LCD_BLON $end
    $var wire 1 , o_done_lcd $end
    $var wire 32 > SIZE_DELAY [31:0] $end
    $var wire 32 . count [31:0] $end
    $var wire 32 / ncount [31:0] $end
    $var wire 32 ? DELAY_15ms [31:0] $end
    $var wire 32 @ DELAY_4_1_ms [31:0] $end
    $var wire 32 A DELAY_1_52ms [31:0] $end
    $var wire 32 B DELAY_100us [31:0] $end
    $var wire 32 C DELAY_37us [31:0] $end
    $var wire 32 D DELAY_230ns [31:0] $end
    $var wire 4 7 w_func_i [3:0] $end
    $var wire 4 0 w_func_next [3:0] $end
    $var wire 4 E FUNC_INIT [3:0] $end
    $var wire 4 F FUNC_SETCURSOR [3:0] $end
    $var wire 4 G FUNC_CMD [3:0] $end
    $var wire 4 H FUNC_DATA [3:0] $end
    $var wire 1 1 w_update_func $end
    $var wire 8 8 w_data_i [7:0] $end
    $var wire 8 2 w_data_next [7:0] $end
    $var wire 1 1 w_update_data $end
    $var wire 8 I CMD_CLEAR_DISPLAY [7:0] $end
    $var wire 8 J CMD_RETURN_HOME [7:0] $end
    $var wire 8 K CMD_ENTRY_INCREASE [7:0] $end
    $var wire 8 L CMD_DISPLAY_OFF [7:0] $end
    $var wire 8 M CMD_DISPLAY_ON [7:0] $end
    $var wire 8 N CMD_INIT_LCD [7:0] $end
    $var wire 8 O CMD_LINE_1 [7:0] $end
    $var wire 8 P CMD_LINE_2 [7:0] $end
    $var wire 32 > SIZE_STATE [31:0] $end
    $var wire 32 3 state [31:0] $end
    $var wire 32 9 nstate [31:0] $end
    $var wire 32 Q IDLE [31:0] $end
    $var wire 32 R INIT_SETUP [31:0] $end
    $var wire 32 S INIT_WAIT [31:0] $end
    $var wire 32 T INIT_STEP [31:0] $end
    $var wire 32 U SETCURSOR_SETUP [31:0] $end
    $var wire 32 V SETCURSOR_WAIT [31:0] $end
    $var wire 32 W CMD_SETUP [31:0] $end
    $var wire 32 X CMD_WAIT [31:0] $end
    $var wire 32 Y DATA_SETUP [31:0] $end
    $var wire 32 Z DATA_WAIT [31:0] $end
    $var wire 32 [ DONE [31:0] $end
    $var wire 32 \ DONE_WAIT [31:0] $end
    $var wire 32 ] INIT_DONE [31:0] $end
    $var wire 32 ^ INIT_DONE_WAIT [31:0] $end
    $var wire 32 _ SIZE_STEP [31:0] $end
    $var wire 9 4 init_step [8:0] $end
    $var wire 9 5 ninit_step [8:0] $end
   $upscope $end
  $upscope $end
 $upscope $end
$enddefinitions $end


#0
0#
0$
0%
0&
b00000000 '
b0000 (
0)
0*
0+
0,
b00000000 -
b00000000000000000000000000000000 .
b00000000000000000000000000000001 /
b0000 0
11
b00000000 2
b00000000000000000000000000000000 3
b000000000 4
b000000001 5
06
b0000 7
b00000000 8
b00000000000000000000000000000000 9
b00000000000000000000000000001000 :
b00000000000000000000000000000100 ;
b00000000000000000000000000010100 <
b00000010111110101111000010000000 =
b00000000000000000000000000100000 >
b00000000000000000000000000110010 ?
b00000000000000000000000000011110 @
b00000000000000000000000000010100 A
b00000000000000000000000000001001 B
b00000000000000000000000000000100 C
b00000000000000000000000000000010 D
b0000 E
b0001 F
b0010 G
b0011 H
b00000001 I
b00000010 J
b00000110 K
b00001000 L
b00001100 M
b00111000 N
b10000000 O
b11000000 P
b00000000000000000000000000000000 Q
b00000000000000000000000000000001 R
b00000000000000000000000000000010 S
b00000000000000000000000000000011 T
b00000000000000000000000000000100 U
b00000000000000000000000000000101 V
b00000000000000000000000000000111 W
b00000000000000000000000000001000 X
b00000000000000000000000000001001 Y
b00000000000000000000000000001010 Z
b00000000000000000000000000001011 [
b00000000000000000000000000001100 \
b00000000000000000000000000001101 ]
b00000000000000000000000000001110 ^
b00000000000000000000000000001001 _
#10
16
#20
06
#30
16
#40
06
#50
16
#60
06
#70
16
#80
06
#90
16
#100
1#
06
#110
16
#120
06
#130
16
#140
06
#150
16
#160
06
#170
16
#180
06
#190
16
#200
06
#210
16
#220
06
#230
16
#240
06
#250
16
#260
06
#270
16
#280
06
#290
16
#300
06
#310
16
#320
06
#330
16
#340
06
#350
16
#360
06
#370
16
#380
06
#390
16
#400
06
#410
16
#420
06
#430
16
#440
06
#450
16
#460
06
#470
16
#480
06
#490
16
#500
1%
1&
06
#510
16
#520
06
#530
16
#540
06
#550
16
#560
06
#570
16
#580
06
#590
16
#600
06
#610
16
#620
06
#630
16
#640
06
#650
16
#660
06
#670
16
#680
06
#690
16
#700
06
#710
16
#720
06
#730
16
#740
06
#750
16
#760
06
#770
16
#780
06
#790
16
#800
06
#810
1$
01
b00000000000000000000000000000001 3
16
b00000000000000000000000000000011 9
#820
06
#830
b00000000000000000000000000000011 3
16
b00000000000000000000000000000010 9
#840
06
#850
b00000000000000000000000000000010 3
b000000001 4
b000000010 5
16
#860
06
#870
b00000000000000000000000000000001 .
b00000000000000000000000000000010 /
16
#880
06
#890
b00000000000000000000000000000010 .
b00000000000000000000000000000011 /
16
#900
06
#910
b00000000000000000000000000000011 .
b00000000000000000000000000000100 /
16
#920
06
#930
b00000000000000000000000000000100 .
b00000000000000000000000000000101 /
16
#940
06
#950
b00000000000000000000000000000101 .
b00000000000000000000000000000110 /
16
#960
06
#970
b00000000000000000000000000000110 .
b00000000000000000000000000000111 /
16
#980
06
#990
b00000000000000000000000000000111 .
b00000000000000000000000000001000 /
16
#1000
06
#1010
b00000000000000000000000000001000 .
b00000000000000000000000000001001 /
16
#1020
06
#1030
b00000000000000000000000000001001 .
b00000000000000000000000000001010 /
16
#1040
06
#1050
b00000000000000000000000000001010 .
b00000000000000000000000000001011 /
16
#1060
06
#1070
b00000000000000000000000000001011 .
b00000000000000000000000000001100 /
16
#1080
06
#1090
b00000000000000000000000000001100 .
b00000000000000000000000000001101 /
16
#1100
06
#1110
b00000000000000000000000000001101 .
b00000000000000000000000000001110 /
16
#1120
06
#1130
b00000000000000000000000000001110 .
b00000000000000000000000000001111 /
16
#1140
06
#1150
b00000000000000000000000000001111 .
b00000000000000000000000000010000 /
16
#1160
06
#1170
b00000000000000000000000000010000 .
b00000000000000000000000000010001 /
16
#1180
06
#1190
b00000000000000000000000000010001 .
b00000000000000000000000000010010 /
16
#1200
06
#1210
b00000000000000000000000000010010 .
b00000000000000000000000000010011 /
16
#1220
06
#1230
b00000000000000000000000000010011 .
b00000000000000000000000000010100 /
16
#1240
06
#1250
b00000000000000000000000000010100 .
b00000000000000000000000000010101 /
16
#1260
06
